shippo/__init__.py
shippo/addresses.py
shippo/batches.py
shippo/carrier_accounts.py
shippo/carrier_parcel_templates.py
shippo/customs_declarations.py
shippo/customs_items.py
shippo/debug.py
shippo/manifests.py
shippo/orders.py
shippo/parcels.py
shippo/pickups.py
shippo/rates.py
shippo/rates_at_checkout.py
shippo/refunds.py
shippo/sdk.py
shippo/sdkconfiguration.py
shippo/service_groups.py
shippo/shipments.py
shippo/shippo_accounts.py
shippo/tracking_status.py
shippo/transactions.py
shippo/user_parcel_templates.py
shippo/webhooks.py
shippo/_hooks/__init__.py
shippo/_hooks/registration.py
shippo/_hooks/sdkhooks.py
shippo/_hooks/types.py
shippo/models/__init__.py
shippo/models/components/__init__.py
shippo/models/components/address.py
shippo/models/components/addresscompletecreaterequest.py
shippo/models/components/addresscreaterequest.py
shippo/models/components/addressimporter.py
shippo/models/components/addresspaginatedlist.py
shippo/models/components/addressvalidationresults.py
shippo/models/components/addressvalidationresultsmessage.py
shippo/models/components/addressvalidationresultsmessagecodeenum.py
shippo/models/components/addressvalidationresultsmessagesourceenum.py
shippo/models/components/alcohol.py
shippo/models/components/batch.py
shippo/models/components/batchcreaterequest.py
shippo/models/components/batchshipment.py
shippo/models/components/batchshipmentcreaterequest.py
shippo/models/components/batchshipmentpaginatedlist.py
shippo/models/components/billing.py
shippo/models/components/carrieraccount.py
shippo/models/components/carrieraccountbase.py
shippo/models/components/carrieraccountcanadapostcreateparameters.py
shippo/models/components/carrieraccountcanadapostcreaterequest.py
shippo/models/components/carrieraccountchronopostcreaterequest.py
shippo/models/components/carrieraccountcolissimocreaterequest.py
shippo/models/components/carrieraccountcorreoscreaterequest.py
shippo/models/components/carrieraccountdeutschepostcreaterequest.py
shippo-3.9.0.dist-info/LICENSE
shippo-3.9.0.dist-info/METADATA
shippo-3.9.0.dist-info/WHEEL
shippo-3.9.0.dist-info/top_level.txt
shippo-3.9.0.dist-info/RECORD
