Metadata-Version: 2.1
Name: shippo
Version: 3.9.0
Summary: Shipping API Python library (USPS, FedEx, UPS and more)
Home-page: https://github.com/goshippo/shippo-python-sdk.git
Author: Shippo
License: MIT License
Platform: UNKNOWN
Requires-Python: >=3.8
Provides-Extra: dev
